filemime/__init__.py
filemime/utillity.py
filemime/usr/bin/file.exe
filemime/usr/bin/msys-2.0.dll
filemime/usr/bin/msys-bz2-1.dll
filemime/usr/bin/msys-magic-1.dll
filemime/usr/bin/msys-z.dll
filemime/usr/share/misc/magic.mgc
filemime-0.0.3.data/data/file.exe
filemime-0.0.3.data/data/magic.mgc
filemime-0.0.3.data/data/msys-2.0.dll
filemime-0.0.3.data/data/msys-bz2-1.dll
filemime-0.0.3.data/data/msys-magic-1.dll
filemime-0.0.3.data/data/msys-z.dll
filemime-0.0.3.dist-info/LICENSE
filemime-0.0.3.dist-info/METADATA
filemime-0.0.3.dist-info/WHEEL
filemime-0.0.3.dist-info/top_level.txt
filemime-0.0.3.dist-info/zip-safe
filemime-0.0.3.dist-info/RECORD
